pyresearchutils/__init__.py
pyresearchutils/config_reader.py
pyresearchutils/constants.py
pyresearchutils/initlized_log.py
pyresearchutils/log_folder.py
pyresearchutils/logger.py
pyresearchutils/metric_averaging.py
pyresearchutils/metric_collector.py
pyresearchutils/metric_lister.py
pyresearchutils/seed.py
pyresearchutils/timing.py
pyresearchutils/wandb_helpers.py
pyresearchutils/signal_processing/__init__.py
pyresearchutils/signal_processing/metric.py
pyresearchutils/signal_processing/spectrum.py
pyresearchutils/torch/__init__.py
pyresearchutils/torch/ema.py
pyresearchutils/torch/numpy_dataset.py
pyresearchutils/torch/tensor_helpers.py
pyresearchutils/torch/working_device.py
pyresearchutils-0.2.1.dist-info/LICENSE
pyresearchutils-0.2.1.dist-info/METADATA
pyresearchutils-0.2.1.dist-info/WHEEL
pyresearchutils-0.2.1.dist-info/top_level.txt
pyresearchutils-0.2.1.dist-info/RECORD
